JingtongPythonShujuKexueChuyiFix1/README.md
JingtongPythonShujuKexueChuyiFix1/__init__.py
JingtongPythonShujuKexueChuyiFix1/__main__.py
JingtongPythonShujuKexueChuyiFix1/file.epub
JingtongPythonShujuKexueChuyiFix1/index.html
JingtongPythonShujuKexueChuyiFix1/css/__init__.py
JingtongPythonShujuKexueChuyiFix1/css/annotations.css
JingtongPythonShujuKexueChuyiFix1/css/main.css
JingtongPythonShujuKexueChuyiFix1/css/normalize.css
JingtongPythonShujuKexueChuyiFix1/css/popup.css
JingtongPythonShujuKexueChuyiFix1/font/__init__.py
JingtongPythonShujuKexueChuyiFix1/font/fontello.eot
JingtongPythonShujuKexueChuyiFix1/font/fontello.svg
JingtongPythonShujuKexueChuyiFix1/font/fontello.ttf
JingtongPythonShujuKexueChuyiFix1/font/fontello.woff
JingtongPythonShujuKexueChuyiFix1/img/__init__.py
JingtongPythonShujuKexueChuyiFix1/img/annotator-glyph-sprite.png
JingtongPythonShujuKexueChuyiFix1/img/annotator-icon-sprite.png
JingtongPythonShujuKexueChuyiFix1/img/apple-touch-icon.png
JingtongPythonShujuKexueChuyiFix1/img/cancelfullscreen.png
JingtongPythonShujuKexueChuyiFix1/img/close.png
JingtongPythonShujuKexueChuyiFix1/img/fullscreen.png
JingtongPythonShujuKexueChuyiFix1/img/loader.gif
JingtongPythonShujuKexueChuyiFix1/img/menu-icon.png
JingtongPythonShujuKexueChuyiFix1/img/save.png
JingtongPythonShujuKexueChuyiFix1/img/saved.png
JingtongPythonShujuKexueChuyiFix1/img/settings-s.png
JingtongPythonShujuKexueChuyiFix1/img/settings.png
JingtongPythonShujuKexueChuyiFix1/img/star.png
JingtongPythonShujuKexueChuyiFix1/js/__init__.py
JingtongPythonShujuKexueChuyiFix1/js/epub.js
JingtongPythonShujuKexueChuyiFix1/js/epub.min.js
JingtongPythonShujuKexueChuyiFix1/js/epub.min.map
JingtongPythonShujuKexueChuyiFix1/js/hooks.min.js
JingtongPythonShujuKexueChuyiFix1/js/hooks.min.map
JingtongPythonShujuKexueChuyiFix1/js/reader.js
JingtongPythonShujuKexueChuyiFix1/js/reader.js.map
JingtongPythonShujuKexueChuyiFix1/js/reader.min.js
JingtongPythonShujuKexueChuyiFix1/js/reader.min.map
jingtong_python_shuju_kexue_chuyi_fix1-2025.3.25.1.dist-info/METADATA
jingtong_python_shuju_kexue_chuyi_fix1-2025.3.25.1.dist-info/WHEEL
jingtong_python_shuju_kexue_chuyi_fix1-2025.3.25.1.dist-info/entry_points.txt
jingtong_python_shuju_kexue_chuyi_fix1-2025.3.25.1.dist-info/top_level.txt
jingtong_python_shuju_kexue_chuyi_fix1-2025.3.25.1.dist-info/RECORD
